everything_cli/__init__.py
everything_cli/everything.py
everything_cli-0.1.1.dist-info/licenses/LICENSE
everything_cli-0.1.1.dist-info/METADATA
everything_cli-0.1.1.dist-info/WHEEL
everything_cli-0.1.1.dist-info/entry_points.txt
everything_cli-0.1.1.dist-info/top_level.txt
everything_cli-0.1.1.dist-info/RECORD
